Metadata-Version: 2.1
Name: odoo12-addon-base-rest-datamodel
Version: 12.0.3.0.1
Summary: Datamodel binding for base_rest
Home-page: https://github.com/OCA/rest-framework
Author: ACSONE SA/NV,Odoo Community Association (OCA)
Author-email: support@odoo-community.org
License: LGPL-3
Platform: UNKNOWN
Classifier: Programming Language :: Python
Classifier: Framework :: Odoo
Classifier: Framework :: Odoo :: 12.0
Classifier: License :: OSI Approved :: GNU Lesser General Public License v3 (LGPLv3)
Requires-Python: >=3.5
Requires-Dist: apispec
Requires-Dist: marshmallow
Requires-Dist: odoo12-addon-base-rest
Requires-Dist: odoo12-addon-datamodel
Requires-Dist: odoo (<12.1dev,>=12.0a)
